LICENSE.md
README.md
setup.py
ntropy/__init__.py
ntropy/ntropy.py
ntropy_timer.egg-info/PKG-INFO
ntropy_timer.egg-info/SOURCES.txt
ntropy_timer.egg-info/dependency_links.txt
ntropy_timer.egg-info/top_level.txt