Metadata-Version: 2.1
Name: ntropy-timer
Version: 0.0.2
Summary: Human readable function time measuring.
Home-page: https://github.com/cacauisadog/ntropy
Author: Cauê Bittencourt Carnietto
Author-email: cbcaue@protonmail.com
License: MIT
Keywords: profiling tuning
Classifier: Programming Language :: Python :: 3
Classifier: License :: OSI Approved :: MIT License
Classifier: Operating System :: OS Independent
License-File: LICENSE.md
